rax_services_python_novaclient_ext
